{
  "id": "b64da2f0-0c46-4a87-9ca5-d8f80d3b5209",
  "prevId": "00000000-0000-0000-0000-000000000000",
  "version": "7",
  "dialect": "postgresql",
  "tables": {
    "public.papertrail_boards": {
      "name": "papertrail_boards",
      "schema": "",
      "columns": {
        "id": {
          "name": "id",
          "type": "text",
          "primaryKey": true,
          "notNull": true
        },
        "tenant_id": {
          "name": "tenant_id",
          "type": "text",
          "primaryKey": false,
          "notNull": true
        },
        "project_id": {
          "name": "project_id",
          "type": "text",
          "primaryKey": false,
          "notNull": true
        },
        "title": {
          "name": "title",
          "type": "text",
          "primaryKey": false,
          "notNull": true
        },
        "version": {
          "name": "version",
          "type": "integer",
          "primaryKey": false,
          "notNull": true,
          "default": 0
        },
        "created_at": {
          "name": "created_at",
          "type": "integer",
          "primaryKey": false,
          "notNull": true
        },
        "updated_at": {
          "name": "updated_at",
          "type": "integer",
          "primaryKey": false,
          "notNull": true
        }
      },
      "indexes": {
        "papertrail_boards_project_idx": {
          "name": "papertrail_boards_project_idx",
          "columns": [
            {
              "expression": "project_id",
              "isExpression": false,
              "asc": true,
              "nulls": "last"
            }
          ],
          "isUnique": false,
          "concurrently": false,
          "method": "btree",
          "with": {}
        }
      },
      "foreignKeys": {},
      "compositePrimaryKeys": {},
      "uniqueConstraints": {},
      "policies": {},
      "checkConstraints": {},
      "isRLSEnabled": false
    },
    "public.papertrail_edges": {
      "name": "papertrail_edges",
      "schema": "",
      "columns": {
        "id": {
          "name": "id",
          "type": "text",
          "primaryKey": true,
          "notNull": true
        },
        "tenant_id": {
          "name": "tenant_id",
          "type": "text",
          "primaryKey": false,
          "notNull": true
        },
        "board_id": {
          "name": "board_id",
          "type": "text",
          "primaryKey": false,
          "notNull": true
        },
        "source": {
          "name": "source",
          "type": "text",
          "primaryKey": false,
          "notNull": true
        },
        "target": {
          "name": "target",
          "type": "text",
          "primaryKey": false,
          "notNull": true
        },
        "data": {
          "name": "data",
          "type": "text",
          "primaryKey": false,
          "notNull": false
        },
        "created_at": {
          "name": "created_at",
          "type": "integer",
          "primaryKey": false,
          "notNull": true
        },
        "updated_at": {
          "name": "updated_at",
          "type": "integer",
          "primaryKey": false,
          "notNull": true
        }
      },
      "indexes": {
        "papertrail_edges_board_idx": {
          "name": "papertrail_edges_board_idx",
          "columns": [
            {
              "expression": "board_id",
              "isExpression": false,
              "asc": true,
              "nulls": "last"
            }
          ],
          "isUnique": false,
          "concurrently": false,
          "method": "btree",
          "with": {}
        }
      },
      "foreignKeys": {},
      "compositePrimaryKeys": {},
      "uniqueConstraints": {},
      "policies": {},
      "checkConstraints": {},
      "isRLSEnabled": false
    },
    "public.papertrail_nodes": {
      "name": "papertrail_nodes",
      "schema": "",
      "columns": {
        "id": {
          "name": "id",
          "type": "text",
          "primaryKey": true,
          "notNull": true
        },
        "tenant_id": {
          "name": "tenant_id",
          "type": "text",
          "primaryKey": false,
          "notNull": true
        },
        "board_id": {
          "name": "board_id",
          "type": "text",
          "primaryKey": false,
          "notNull": true
        },
        "type": {
          "name": "type",
          "type": "text",
          "primaryKey": false,
          "notNull": true
        },
        "data": {
          "name": "data",
          "type": "text",
          "primaryKey": false,
          "notNull": true
        },
        "position": {
          "name": "position",
          "type": "text",
          "primaryKey": false,
          "notNull": true
        },
        "created_at": {
          "name": "created_at",
          "type": "integer",
          "primaryKey": false,
          "notNull": true
        },
        "updated_at": {
          "name": "updated_at",
          "type": "integer",
          "primaryKey": false,
          "notNull": true
        }
      },
      "indexes": {
        "papertrail_nodes_board_idx": {
          "name": "papertrail_nodes_board_idx",
          "columns": [
            {
              "expression": "board_id",
              "isExpression": false,
              "asc": true,
              "nulls": "last"
            }
          ],
          "isUnique": false,
          "concurrently": false,
          "method": "btree",
          "with": {}
        }
      },
      "foreignKeys": {},
      "compositePrimaryKeys": {},
      "uniqueConstraints": {},
      "policies": {},
      "checkConstraints": {},
      "isRLSEnabled": false
    },
    "public.papertrail_project_members": {
      "name": "papertrail_project_members",
      "schema": "",
      "columns": {
        "project_id": {
          "name": "project_id",
          "type": "text",
          "primaryKey": false,
          "notNull": true
        },
        "tenant_id": {
          "name": "tenant_id",
          "type": "text",
          "primaryKey": false,
          "notNull": true
        },
        "user_id": {
          "name": "user_id",
          "type": "text",
          "primaryKey": false,
          "notNull": true
        },
        "role": {
          "name": "role",
          "type": "text",
          "primaryKey": false,
          "notNull": true
        },
        "invited_by": {
          "name": "invited_by",
          "type": "text",
          "primaryKey": false,
          "notNull": false
        },
        "joined_at": {
          "name": "joined_at",
          "type": "integer",
          "primaryKey": false,
          "notNull": true
        }
      },
      "indexes": {
        "papertrail_project_members_project_idx": {
          "name": "papertrail_project_members_project_idx",
          "columns": [
            {
              "expression": "project_id",
              "isExpression": false,
              "asc": true,
              "nulls": "last"
            }
          ],
          "isUnique": false,
          "concurrently": false,
          "method": "btree",
          "with": {}
        }
      },
      "foreignKeys": {},
      "compositePrimaryKeys": {
        "papertrail_project_members_project_id_user_id_pk": {
          "name": "papertrail_project_members_project_id_user_id_pk",
          "columns": [
            "project_id",
            "user_id"
          ]
        }
      },
      "uniqueConstraints": {},
      "policies": {},
      "checkConstraints": {},
      "isRLSEnabled": false
    },
    "public.papertrail_projects": {
      "name": "papertrail_projects",
      "schema": "",
      "columns": {
        "id": {
          "name": "id",
          "type": "text",
          "primaryKey": true,
          "notNull": true
        },
        "tenant_id": {
          "name": "tenant_id",
          "type": "text",
          "primaryKey": false,
          "notNull": true
        },
        "created_by": {
          "name": "created_by",
          "type": "text",
          "primaryKey": false,
          "notNull": true
        },
        "name": {
          "name": "name",
          "type": "text",
          "primaryKey": false,
          "notNull": true
        },
        "description": {
          "name": "description",
          "type": "text",
          "primaryKey": false,
          "notNull": false
        },
        "archived_at": {
          "name": "archived_at",
          "type": "integer",
          "primaryKey": false,
          "notNull": false
        },
        "created_at": {
          "name": "created_at",
          "type": "integer",
          "primaryKey": false,
          "notNull": true
        },
        "updated_at": {
          "name": "updated_at",
          "type": "integer",
          "primaryKey": false,
          "notNull": true
        }
      },
      "indexes": {},
      "foreignKeys": {},
      "compositePrimaryKeys": {},
      "uniqueConstraints": {},
      "policies": {},
      "checkConstraints": {},
      "isRLSEnabled": false
    }
  },
  "enums": {},
  "schemas": {},
  "sequences": {},
  "roles": {},
  "policies": {},
  "views": {},
  "_meta": {
    "columns": {},
    "schemas": {},
    "tables": {}
  }
}